LICENSE
README.rst
pyproject.toml
setup.cfg
setup.py
crypton/__init__.py
crypton/main.py
crypton/py.typed
crypton/affine/__init__.py
crypton/affine/src/__init__.py
crypton/affine/src/affine_decrypt.py
crypton/affine/src/affine_encrypt.py
crypton/affine/src/affine_helper.py
crypton/block/__init__.py
crypton/block/src/__init__.py
crypton/block/src/block_decrypt.py
crypton/block/src/block_encrypt.py
crypton/block/src/block_helper.py
crypton/utils/__init__.py
crypton/utils/cryption.py
crypton/utils/math.py
crypton/utils/space.py
pycrypton.egg-info/PKG-INFO
pycrypton.egg-info/SOURCES.txt
pycrypton.egg-info/dependency_links.txt
pycrypton.egg-info/not-zip-safe
pycrypton.egg-info/requires.txt
pycrypton.egg-info/top_level.txt