Metadata-Version: 2.1
Name: pycrypton
Version: 1.3.1
Summary: Crypt with Crypton
Author: Batuhan INAN
License: MIT
Platform: unix
Platform: linux
Platform: osx
Platform: cygwin
Platform: win32
Classifier: Programming Language :: Python :: 3 :: Only
Classifier: Programming Language :: Python :: 3.7
Classifier: Programming Language :: Python :: 3.8
Classifier: Programming Language :: Python :: 3.9
Requires-Python: >=3.7
Provides-Extra: testing
License-File: LICENSE
